omnimcp/__init__.py
omnimcp/log.py
omnimcp/main.py
omnimcp/mcp_engine.py
omnimcp/mcp_server.py
omnimcp/services/content_manager.py
omnimcp/services/descriptor.py
omnimcp/services/embedding.py
omnimcp/services/index.py
omnimcp/settings.py
omnimcp/tools/__init__.py
omnimcp/tools/execute_tool.py
omnimcp/tools/get_content.py
omnimcp/tools/get_server_info.py
omnimcp/tools/get_tool_details.py
omnimcp/tools/list_running_servers.py
omnimcp/tools/list_server_tools.py
omnimcp/tools/manage_server.py
omnimcp/tools/poll_task_result.py
omnimcp/tools/search_tools.py
omnimcp/types.py
omnimcp/utilities.py
omnimcp-0.1.1.dist-info/WHEEL
omnimcp-0.1.1.dist-info/entry_points.txt
omnimcp-0.1.1.dist-info/METADATA
omnimcp-0.1.1.dist-info/RECORD
