Metadata-Version: 2.3
Name: omnimcp
Version: 0.1.1
Summary: Semantic router for MCP ecosystems - Discover and execute tools across multiple MCP servers without context bloat
Keywords: mcp,model-context-protocol,semantic-search,llm,ai-agents,tool-routing,omnimcp
Author: BA Ibrahima
Author-email: BA Ibrahima <ibrahima.elmokhtar@gmail.com>
License: MIT
Classifier: Development Status :: 4 - Beta
Classifier: Intended Audience :: Developers
Classifier: License :: OSI Approved :: MIT License
Classifier: Programming Language :: Python :: 3
Classifier: Programming Language :: Python :: 3.12
Classifier: Topic :: Software Development :: Libraries :: Python Modules
Requires-Dist: click>=8.3.1
Requires-Dist: fastmcp>=2.13.1
Requires-Dist: mcp>=1.22.0
Requires-Dist: openai>=2.8.1
Requires-Dist: pydantic>=2.12.4
Requires-Dist: pydantic-settings>=2.12.0
Requires-Dist: pyzmq>=27.1.0
Requires-Dist: qdrant-client>=1.16.0
Requires-Dist: tenacity>=9.1.2
Requires-Dist: tiktoken>=0.12.0
Requires-Python: >=3.12
Project-URL: Homepage, https://github.com/milkymap/omnimcp
Project-URL: Issues, https://github.com/milkymap/omnimcp/issues
Project-URL: Repository, https://github.com/milkymap/omnimcp
